deltaxplainer
