Metadata-Version: 2.1
Name: deltaxplainer
Version: 1.1.2
Summary: A package for DeltaXplainer model implemented from the paper https://arxiv.org/pdf/2309.17095.pdf
Home-page: UNKNOWN
Author: Adam Rida
License: UNKNOWN
Platform: UNKNOWN
